Workbook

Sheet Product Master
A1: ProductID | B1: ProductName | C1: Category | D1: Supplier | E1: StandardCost | F1: StandardPrice | G1: ReorderLevel | H1: CurrentStock | I1: LeadTimeDays
A2: P001 | B2: Laptop Pro 15 | C2: Laptops | D2: TechGlobal | E2: 1200 | F2: 1800 | G2: 20 | H2: 15 | I2: 5
A3: P002 | B3: Smartphone X | C3: Phones | D3: MobileSource | E3: 600 | F3: 900 | G3: 50 | H3: 40 | I3: 3
A4: P003 | B4: Wireless Earbuds | C4: Audio | D4: SoundWave | E4: 80 | F4: 120 | G4: 100 | H4: 120 | I4: 2
A5: P004 | B5: Mechanical Keyboard | C5: Accessories | D5: KeyMasters | E5: 100 | F5: 150 | G5: 30 | H5: 25 | I5: 4
A6: P005 | B6: All-in-One PC | C6: Office Equipment | D6: OfficeTech | E6: 900 | F6: 1350 | G6: 15 | H6: 10 | I6: 7
A7: P006 | B7: Gaming Console Gen 5 | C7: Gaming | D7: GameWorld | E7: 400 | F7: 600 | G7: 25 | H7: 30 | I7: 6
A8: P007 | B8: Laptop Air 13 | C8: Laptops | D8: TechGlobal | E8: 1000 | F8: 1500 | G8: 25 | H8: 20 | I8: 5
A9: P008 | B9: Smartphone Lite | C9: Phones | D9: MobileSource | E9: 300 | F9: 450 | G9: 60 | H9: 70 | I9: 3
A10: P009 | B10: Bluetooth Speaker | C10: Audio | D10: SoundWave | E10: 50 | F10: 75 | G10: 150 | H10: 180 | I10: 2
A11: P010 | B11: Ergonomic Mouse | C11: Accessories | D11: KeyMasters | E11: 40 | F11: 60 | G11: 50 | H11: 60 | I11: 2
A12: P011 | B12: Office Monitor 27" | C12: Office Equipment | D12: OfficeTech | E12: 250 | F12: 375 | G12: 20 | H12: 22 | I12: 4
A13: P012 | B13: Gaming Keyboard RGB | C13: Gaming | D13: GameWorld | E13: 120 | F13: 180 | G13: 35 | H13: 40 | I13: 3
... A41: P040 | B41: Smartwatch | C41: Accessories | D41: WearableTech | E41: 200 | F41: 300 | G41: 60 | H41: 70 | I41: 2

Sheet Sales Data
A1: OrderID | B1: OrderDate | C1: CustomerName | D1: CustomerSegment | E1: Region | F1: Salesperson | G1: ProductID | H1: ProductName | I1: Category | J1: UnitsSold | K1: UnitPrice | L1: DiscountPercent | M1: Revenue | N1: Cost | O1: GrossProfit | P1: GrossMargin | Q1: OrderStatus
A2: ORD-1001 | B2: 45406 | C2: Alpha Corp | D2: Enterprise | E2: East | F2: Bob Jones | G2: P008 | H2: Smartphone Lite | I2: Phones | J2: 3 | K2: 460.64 | L2: 0.15 | M2: =J2*K2*(1-L2) -> 1174.632 | N2: =P5 -> 0.35 | O2: =M2-N2 -> 1174.282 | P2: =IFERROR(O2/M2, 0) -> 0.99970203 | Q2: Completed
A3: ORD-1002 | B3: 45724 | C3: Alpha Corp | D3: Consumer | E3: North | F3: Bob Jones | G3: P008 | H3: Smartphone Lite | I3: Phones | J3: 9 | K3: 454.59 | L3: 0.15 | M3: =J3*K3*(1-L3) -> 3477.6135 | N3: =M3*0.65 -> 2260.4488 | O3: =M3-N3 -> 1217.1647 | P3: =IFERROR(O3/M3, 0) -> 0.35 | Q3: Completed
A4: ORD-1003 | B4: 45721 | C4: Delta Retail | D4: SMB | E4: East | F4: Alice Smith | G4: P006 | H4: Gaming Console Gen 5 | I4: Gaming | J4: 12 | K4: 595.36 | L4: 0.05 | M4: =J4*K4*(1-L4) -> 6787.104 | N4: =M4*0.65 -> 4411.6176 | O4: =M4-N4 -> 2375.4864 | P4: =IFERROR(O4/M4, 0) -> 0.35 | Q4: Completed
A5: ORD-1004 | B5: 45512 | C5: Prime Logistics | D5: SMB | E5: North | F5: Alice Smith | G5: P013 | H5: Laptop Workstation | I5: Laptops | J5: 2 | K5: 2218.27 | L5: 0.05 | M5: =J5*K5*(1-L5) -> 4214.713 | N5: =M5*0.65 -> 2739.5635 | O5: =M5-N5 -> 1475.1495 | P5: =IFERROR(O5/M5, 0) -> 0.35 | Q5: Pending
A6: ORD-1005 | B6: 45562 | C6: Prime Logistics | D6: Consumer | E6: West | F6: Ethan Hunt | G6: P004 | H6: Mechanical Keyboard | I6: Accessories | J6: 15 | K6: 148.18 | L6: 0.15 | M6: =J6*K6*(1-L6) -> 1889.295 | N6: =M6*0.65 -> 1228.0418 | O6: =M6-N6 -> 661.25325 | P6: =IFERROR(O6/M6, 0) -> 0.35 | Q6: Completed
A7: ORD-1006 | B7: 45662 | C7: Pioneer Media | D7: Consumer | E7: North | F7: Alice Smith | G7: P008 | H7: Smartphone Lite | I7: Phones | J7: 13 | K7: 440.52 | L7: 0 | M7: =J7*K7*(1-L7) -> 5726.76 | N7: =M7*0.65 -> 3722.394 | O7: =M7-N7 -> 2004.366 | P7: =IFERROR(O7/M7, 0) -> 0.35 | Q7: Completed
A8: ORD-1007 | B8: 45395 | C8: Omega Tech | D8: SMB | E8: West | F8: Fiona Gallagher | G8: P012 | H8: Gaming Keyboard RGB | I8: Gaming | J8: 3 | K8: 177.66 | L8: 0 | M8: =J8*K8*(1-L8) -> 532.98 | N8: =M8*0.65 -> 346.437 | O8: =M8-N8 -> 186.543 | P8: =IFERROR(O8/M8, 0) -> 0.35 | Q8: Cancelled
A9: ORD-1008 | B9: 45565 | C9: Nova Systems | D9: Enterprise | E9: North | F9: Ethan Hunt | G9: P006 | H9: Gaming Console Gen 5 | I9: Gaming | J9: 9 | K9: 613.75 | L9: 0 | M9: =J9*K9*(1-L9) -> 5523.75 | N9: =M9*0.65 -> 3590.4375 | O9: =M9-N9 -> 1933.3125 | P9: =IFERROR(O9/M9, 0) -> 0.35 | Q9: Shipped
A10: ORD-1009 | B10: 45680 | C10: Epsilon Group | D10: Enterprise | E10: South | F10: Fiona Gallagher | G10: P011 | H10: Office Monitor 27" | I10: Office Equipment | J10: 14 | K10: 385.06 | L10: 0 | M10: =J10*K10*(1-L10) -> 5390.84 | N10: =M10*0.65 -> 3504.046 | O10: =M10-N10 -> 1886.794 | P10: =IFERROR(O10/M10, 0) -> 0.35 | Q10: Completed
A11: ORD-1010 | B11: 45324 | C11: Prime Logistics | D11: SMB | E11: West | F11: Charlie Brown | G11: P003 | H11: Wireless Earbuds | I11: Audio | J11: 4 | K11: 124.96 | L11: 0.15 | M11: =J11*K11*(1-L11) -> 424.864 | N11: =M11*0.65 -> 276.1616 | O11: =M11-N11 -> 148.7024 | P11: =IFERROR(O11/M11, 0) -> 0.35 | Q11: Cancelled
A12: ORD-1011 | B12: 45614 | C12: Delta Retail | D12: Enterprise | E12: West | F12: Diana Prince | G12: P015 | H12: Noise Cancelling Headphones | I12: Audio | J12: 3 | K12: 219.71 | L12: 0 | M12: =J12*K12*(1-L12) -> 659.13 | N12: =M12*0.65 -> 428.4345 | O12: =M12-N12 -> 230.6955 | P12: =IFERROR(O12/M12, 0) -> 0.35 | Q12: Cancelled
A13: ORD-1012 | B13: 45561 | C13: Nova Systems | D13: Enterprise | E13: West | F13: Ethan Hunt | G13: P013 | H13: Laptop Workstation | I13: Laptops | J13: 6 | K13: 2186.85 | L13: 0 | M13: =J13*K13*(1-L13) -> 13121.1 | N13: =M13*0.65 -> 8528.715 | O13: =M13-N13 -> 4592.385 | P13: =IFERROR(O13/M13, 0) -> 0.35 | Q13: Pending
A14: ORD-1013 | B14: 45797 | C14: Beta LLC | D14: Consumer | E14: North | F14: Bob Jones | G14: P006 | H14: Gaming Console Gen 5 | I14: Gaming | J14: 13 | K14: 610.83 | L14: 0.15 | M14: =J14*K14*(1-L14) -> 6749.6715 | N14: =M14*0.65 -> 4387.2865 | O14: =M14-N14 -> 2362.385 | P14: =IFERROR(O14/M14, 0) -> 0.35 | Q14: Completed
... A351: ORD-1350 | B351: 45626 | C351: Omega Tech | D351: Enterprise | E351: North | F351: Charlie Brown | G351: P014 | H351: Smartphone Pro Max | I351: Phones | J351: 12 | K351: 1254.41 | L351: 0 | M351: =J351*K351*(1-L351) -> 15052.92 | N351: =M351*0.65 -> 9784.398 | O351: =M351-N351 -> 5268.522 | P351: =IFERROR(O351/M351, 0) -> 0.35 | Q351: Completed

Sheet Monthly Budget
A1: Month | B1: Region | C1: RevenueTarget | D1: ActualRevenue | E1: RevenueVariance | F1: GrossProfitTarget | G1: ActualGrossProfit | H1: GrossProfitVariance | I1: TargetStatus
A2: 2024-01 | B2: North | C2: 50000 | D2: =SUMIFS(SalesData[Revenue], SalesData[Region], B2, SalesData[OrderDate], ">="&DATE(LEFT(A2,4),MID(A2,6,2),1), SalesData[OrderDate], "<="&EOMONTH(DATE(LEFT(A2,4),MID(A2,6,2),1),0)) -> 11539.115 | E2: =D2-C2 -> -38460.885 | F2: 18000 | G2: =SUMIFS(SalesData[GrossProfit], SalesData[Region], B2, SalesData[OrderDate], ">="&DATE(LEFT(A2,4),MID(A2,6,2),1), SalesData[OrderDate], "<="&EOMONTH(DATE(LEFT(A2,4),MID(A2,6,2),1),0)) -> 4038.6904 | H2: =G2-F2 -> -13961.31 | I2: =IF(D2>=C2, "Met", "Missed") -> Missed
A3: 2024-01 | B3: South | C3: 50000 | D3: =SUMIFS(SalesData[Revenue], SalesData[Region], B3, SalesData[OrderDate], ">="&DATE(LEFT(A3,4),MID(A3,6,2),1), SalesData[OrderDate], "<="&EOMONTH(DATE(LEFT(A3,4),MID(A3,6,2),1),0)) -> 7008.7425 | E3: =D3-C3 -> -42991.257 | F3: 18000 | G3: =SUMIFS(SalesData[GrossProfit], SalesData[Region], B3, SalesData[OrderDate], ">="&DATE(LEFT(A3,4),MID(A3,6,2),1), SalesData[OrderDate], "<="&EOMONTH(DATE(LEFT(A3,4),MID(A3,6,2),1),0)) -> 2453.0599 | H3: =G3-F3 -> -15546.94 | I3: =IF(D3>=C3, "Met", "Missed") -> Missed
A4: 2024-01 | B4: East | C4: 50000 | D4: =SUMIFS(SalesData[Revenue], SalesData[Region], B4, SalesData[OrderDate], ">="&DATE(LEFT(A4,4),MID(A4,6,2),1), SalesData[OrderDate], "<="&EOMONTH(DATE(LEFT(A4,4),MID(A4,6,2),1),0)) -> 9788.5185 | E4: =D4-C4 -> -40211.482 | F4: 18000 | G4: =SUMIFS(SalesData[GrossProfit], SalesData[Region], B4, SalesData[OrderDate], ">="&DATE(LEFT(A4,4),MID(A4,6,2),1), SalesData[OrderDate], "<="&EOMONTH(DATE(LEFT(A4,4),MID(A4,6,2),1),0)) -> 3425.9815 | H4: =G4-F4 -> -14574.019 | I4: =IF(D4>=C4, "Met", "Missed") -> Missed
A5: 2024-01 | B5: West | C5: 50000 | D5: =SUMIFS(SalesData[Revenue], SalesData[Region], B5, SalesData[OrderDate], ">="&DATE(LEFT(A5,4),MID(A5,6,2),1), SalesData[OrderDate], "<="&EOMONTH(DATE(LEFT(A5,4),MID(A5,6,2),1),0)) -> 9960.774 | E5: =D5-C5 -> -40039.226 | F5: 18000 | G5: =SUMIFS(SalesData[GrossProfit], SalesData[Region], B5, SalesData[OrderDate], ">="&DATE(LEFT(A5,4),MID(A5,6,2),1), SalesData[OrderDate], "<="&EOMONTH(DATE(LEFT(A5,4),MID(A5,6,2),1),0)) -> 3486.2709 | H5: =G5-F5 -> -14513.729 | I5: =IF(D5>=C5, "Met", "Missed") -> Missed
A6: 2024-02 | B6: North | C6: 50000 | D6: =SUMIFS(SalesData[Revenue], SalesData[Region], B6, SalesData[OrderDate], ">="&DATE(LEFT(A6,4),MID(A6,6,2),1), SalesData[OrderDate], "<="&EOMONTH(DATE(LEFT(A6,4),MID(A6,6,2),1),0)) -> 36553.925 | E6: =D6-C6 -> -13446.075 | F6: 18000 | G6: =SUMIFS(SalesData[GrossProfit], SalesData[Region], B6, SalesData[OrderDate], ">="&DATE(LEFT(A6,4),MID(A6,6,2),1), SalesData[OrderDate], "<="&EOMONTH(DATE(LEFT(A6,4),MID(A6,6,2),1),0)) -> 12793.874 | H6: =G6-F6 -> -5206.1264 | I6: =IF(D6>=C6, "Met", "Missed") -> Missed
A7: 2024-02 | B7: South | C7: 50000 | D7: =SUMIFS(SalesData[Revenue], SalesData[Region], B7, SalesData[OrderDate], ">="&DATE(LEFT(A7,4),MID(A7,6,2),1), SalesData[OrderDate], "<="&EOMONTH(DATE(LEFT(A7,4),MID(A7,6,2),1),0)) -> 8991.7555 | E7: =D7-C7 -> -41008.245 | F7: 18000 | G7: =SUMIFS(SalesData[GrossProfit], SalesData[Region], B7, SalesData[OrderDate], ">="&DATE(LEFT(A7,4),MID(A7,6,2),1), SalesData[OrderDate], "<="&EOMONTH(DATE(LEFT(A7,4),MID(A7,6,2),1),0)) -> 3147.1144 | H7: =G7-F7 -> -14852.886 | I7: =IF(D7>=C7, "Met", "Missed") -> Missed
A8: 2024-02 | B8: East | C8: 50000 | D8: =SUMIFS(SalesData[Revenue], SalesData[Region], B8, SalesData[OrderDate], ">="&DATE(LEFT(A8,4),MID(A8,6,2),1), SalesData[OrderDate], "<="&EOMONTH(DATE(LEFT(A8,4),MID(A8,6,2),1),0)) -> 17055.718 | E8: =D8-C8 -> -32944.282 | F8: 18000 | G8: =SUMIFS(SalesData[GrossProfit], SalesData[Region], B8, SalesData[OrderDate], ">="&DATE(LEFT(A8,4),MID(A8,6,2),1), SalesData[OrderDate], "<="&EOMONTH(DATE(LEFT(A8,4),MID(A8,6,2),1),0)) -> 5969.5013 | H8: =G8-F8 -> -12030.499 | I8: =IF(D8>=C8, "Met", "Missed") -> Missed
A9: 2024-02 | B9: West | C9: 50000 | D9: =SUMIFS(SalesData[Revenue], SalesData[Region], B9, SalesData[OrderDate], ">="&DATE(LEFT(A9,4),MID(A9,6,2),1), SalesData[OrderDate], "<="&EOMONTH(DATE(LEFT(A9,4),MID(A9,6,2),1),0)) -> 39107.438 | E9: =D9-C9 -> -10892.562 | F9: 18000 | G9: =SUMIFS(SalesData[GrossProfit], SalesData[Region], B9, SalesData[OrderDate], ">="&DATE(LEFT(A9,4),MID(A9,6,2),1), SalesData[OrderDate], "<="&EOMONTH(DATE(LEFT(A9,4),MID(A9,6,2),1),0)) -> 13687.603 | H9: =G9-F9 -> -4312.3965 | I9: =IF(D9>=C9, "Met", "Missed") -> Missed
A10: 2024-03 | B10: North | C10: 50000 | D10: =SUMIFS(SalesData[Revenue], SalesData[Region], B10, SalesData[OrderDate], ">="&DATE(LEFT(A10,4),MID(A10,6,2),1), SalesData[OrderDate], "<="&EOMONTH(DATE(LEFT(A10,4),MID(A10,6,2),1),0)) -> 57576.931 | E10: =D10-C10 -> 7576.9305 | F10: 18000 | G10: =SUMIFS(SalesData[GrossProfit], SalesData[Region], B10, SalesData[OrderDate], ">="&DATE(LEFT(A10,4),MID(A10,6,2),1), SalesData[OrderDate], "<="&EOMONTH(DATE(LEFT(A10,4),MID(A10,6,2),1),0)) -> 20151.926 | H10: =G10-F10 -> 2151.9257 | I10: =IF(D10>=C10, "Met", "Missed") -> Met
A11: 2024-03 | B11: South | C11: 50000 | D11: =SUMIFS(SalesData[Revenue], SalesData[Region], B11, SalesData[OrderDate], ">="&DATE(LEFT(A11,4),MID(A11,6,2),1), SalesData[OrderDate], "<="&EOMONTH(DATE(LEFT(A11,4),MID(A11,6,2),1),0)) -> 50404.389 | E11: =D11-C11 -> 404.389 | F11: 18000 | G11: =SUMIFS(SalesData[GrossProfit], SalesData[Region], B11, SalesData[OrderDate], ">="&DATE(LEFT(A11,4),MID(A11,6,2),1), SalesData[OrderDate], "<="&EOMONTH(DATE(LEFT(A11,4),MID(A11,6,2),1),0)) -> 17641.536 | H11: =G11-F11 -> -358.46385 | I11: =IF(D11>=C11, "Met", "Missed") -> Met
A12: 2024-03 | B12: East | C12: 50000 | D12: =SUMIFS(SalesData[Revenue], SalesData[Region], B12, SalesData[OrderDate], ">="&DATE(LEFT(A12,4),MID(A12,6,2),1), SalesData[OrderDate], "<="&EOMONTH(DATE(LEFT(A12,4),MID(A12,6,2),1),0)) -> 46470.953 | E12: =D12-C12 -> -3529.0475 | F12: 18000 | G12: =SUMIFS(SalesData[GrossProfit], SalesData[Region], B12, SalesData[OrderDate], ">="&DATE(LEFT(A12,4),MID(A12,6,2),1), SalesData[OrderDate], "<="&EOMONTH(DATE(LEFT(A12,4),MID(A12,6,2),1),0)) -> 16264.833 | H12: =G12-F12 -> -1735.1666 | I12: =IF(D12>=C12, "Met", "Missed") -> Missed
A13: 2024-03 | B13: West | C13: 50000 | D13: =SUMIFS(SalesData[Revenue], SalesData[Region], B13, SalesData[OrderDate], ">="&DATE(LEFT(A13,4),MID(A13,6,2),1), SalesData[OrderDate], "<="&EOMONTH(DATE(LEFT(A13,4),MID(A13,6,2),1),0)) -> 15925.905 | E13: =D13-C13 -> -34074.095 | F13: 18000 | G13: =SUMIFS(SalesData[GrossProfit], SalesData[Region], B13, SalesData[OrderDate], ">="&DATE(LEFT(A13,4),MID(A13,6,2),1), SalesData[OrderDate], "<="&EOMONTH(DATE(LEFT(A13,4),MID(A13,6,2),1),0)) -> 5574.0668 | H13: =G13-F13 -> -12425.933 | I13: =IF(D13>=C13, "Met", "Missed") -> Missed
... A73: 2025-06 | B73: West | C73: 50000 | D73: =SUMIFS(SalesData[Revenue], SalesData[Region], B73, SalesData[OrderDate], ">="&DATE(LEFT(A73,4),MID(A73,6,2),1), SalesData[OrderDate], "<="&EOMONTH(DATE(LEFT(A73,4),MID(A73,6,2),1),0)) -> 26662.99 | E73: =D73-C73 -> -23337.01 | F73: 18000 | G73: =SUMIFS(SalesData[GrossProfit], SalesData[Region], B73, SalesData[OrderDate], ">="&DATE(LEFT(A73,4),MID(A73,6,2),1), SalesData[OrderDate], "<="&EOMONTH(DATE(LEFT(A73,4),MID(A73,6,2),1),0)) -> 9332.0463 | H73: =G73-F73 -> -8667.9537 | I73: =IF(D73>=C73, "Met", "Missed") -> Missed

Sheet Sales Summary
A1: Executive Sales Summary & KPIs
A3: Total Revenue | B3: Total Gross Profit | C3: Gross Margin % | D3: Units Sold | E3: Average Order Value | F3: Completed Orders
A4: =SUM(SalesData[Revenue]) -> 1788685.3 | B4: =SUM(SalesData[GrossProfit]) -> 626803.02 | C4: =B4/A4 -> 0.35042666 | D4: =SUM(SalesData[UnitsSold]) -> 2840 | E4: =AVERAGE(SalesData[Revenue]) -> 5110.5295 | F4: =COUNTIF(SalesData[OrderStatus], "Completed") -> 182
A7: Region Performance Summary
A8: Region | B8: Revenue | C8: Gross Profit | D8: Gross Margin | E8: Order Count
A9: North | B9: =SUMIF(SalesData[Region], A9, SalesData[Revenue]) -> 392009.97 | C9: =SUMIF(SalesData[Region], A9, SalesData[GrossProfit]) -> 137203.49 | D9: =IFERROR(C9/B9, 0) -> 0.35 | E9: =COUNTIF(SalesData[Region], A9) -> 73
A10: South | B10: =SUMIF(SalesData[Region], A10, SalesData[Revenue]) -> 485650.15 | C10: =SUMIF(SalesData[Region], A10, SalesData[GrossProfit]) -> 169977.55 | D10: =IFERROR(C10/B10, 0) -> 0.35 | E10: =COUNTIF(SalesData[Region], A10) -> 92
A11: East | B11: =SUMIF(SalesData[Region], A11, SalesData[Revenue]) -> 354659.13 | C11: =SUMIF(SalesData[Region], A11, SalesData[GrossProfit]) -> 124893.85 | D11: =IFERROR(C11/B11, 0) -> 0.35215181 | E11: =COUNTIF(SalesData[Region], A11) -> 79
A12: West | B12: =SUMIF(SalesData[Region], A12, SalesData[Revenue]) -> 556366.07 | C12: =SUMIF(SalesData[Region], A12, SalesData[GrossProfit]) -> 194728.12 | D12: =IFERROR(C12/B12, 0) -> 0.35 | E12: =COUNTIF(SalesData[Region], A12) -> 106
A15: Category Performance Summary
A16: Category | B16: Revenue | C16: Gross Profit | D16: Gross Margin | E16: Units Sold
A17: Accessories | B17: =SUMIF(SalesData[Category], A17, SalesData[Revenue]) -> 37587.077 | C17: les Summary'!E17 | D17: =IFERROR(C17/B17, 0) -> 0 | E17: =SUMIF(SalesData[Category], A17, SalesData[UnitsSold]) -> 466
A18: Audio | B18: =SUMIF(SalesData[Category], A18, SalesData[Revenue]) -> 79912.277 | C18: =SUMIF(SalesData[Category], A18, SalesData[GrossProfit]) -> 27969.297 | D18: =IFERROR(C18/B18, 0) -> 0.35 | E18: =SUMIF(SalesData[Category], A18, SalesData[UnitsSold]) -> 542
A19: Gaming | B19: =SUMIF(SalesData[Category], A19, SalesData[Revenue]) -> 163684.37 | C19: =SUMIF(SalesData[Category], A19, SalesData[GrossProfit]) -> 57289.531 | D19: =IFERROR(C19/B19, 0) -> 0.35 | E19: =SUMIF(SalesData[Category], A19, SalesData[UnitsSold]) -> 439
A20: Phones | B20: =SUMIF(SalesData[Category], A20, SalesData[Revenue]) -> 325112.55 | C20: =SUMIF(SalesData[Category], A20, SalesData[GrossProfit]) -> 114552.55 | D20: =IFERROR(C20/B20, 0) -> 0.35234737 | E20: =SUMIF(SalesData[Category], A20, SalesData[UnitsSold]) -> 543
A21: Office Equipment | B21: =SUMIF(SalesData[Category], A21, SalesData[Revenue]) -> 399443.56 | C21: =SUMIF(SalesData[Category], A21, SalesData[GrossProfit]) -> 139805.25 | D21: =IFERROR(C21/B21, 0) -> 0.35 | E21: =SUMIF(SalesData[Category], A21, SalesData[UnitsSold]) -> 397
A22: Laptops | B22: =SUMIF(SalesData[Category], A22, SalesData[Revenue]) -> 782945.47 | C22: =SUMIF(SalesData[Category], A22, SalesData[GrossProfit]) -> 274030.92 | D22: =IFERROR(C22/B22, 0) -> 0.35 | E22: =SUMIF(SalesData[Category], A22, SalesData[UnitsSold]) -> 453

Sheet Customer Analysis
A1: Customer Segment Performance
A2: Customer Segment | B2: Revenue | C2: Gross Profit | D2: Gross Margin | E2: Order Count | F2: Average Order Value
A3: Consumer | B3: =SUMIF(SalesData[CustomerSegment], A3, SalesData[Revenue]) -> 594405.01 | C3: =SUMIF(SalesData[CustomerSegment], A3, SalesData[GrossProfit]) -> 208041.75 | D3: =IFERROR(C3/B3, 0) -> 0.35 | E3: =COUNTIF(SalesData[CustomerSegment], A3) -> 113 | F3: =AVERAGEIF(SalesData[CustomerSegment], A3, SalesData[Revenue]) -> 5260.2213
A4: SMB | B4: =SUMIF(SalesData[CustomerSegment], A4, SalesData[Revenue]) -> 576544.47 | C4: =SUMIF(SalesData[CustomerSegment], A4, SalesData[GrossProfit]) -> 201790.56 | D4: =IFERROR(C4/B4, 0) -> 0.35 | E4: =COUNTIF(SalesData[CustomerSegment], A4) -> 112 | F4: =AVERAGEIF(SalesData[CustomerSegment], A4, SalesData[Revenue]) -> 5147.7184
A5: Enterprise | B5: =SUMIF(SalesData[CustomerSegment], A5, SalesData[Revenue]) -> 617735.83 | C5: =SUMIF(SalesData[CustomerSegment], A5, SalesData[GrossProfit]) -> 216970.7 | D5: =IFERROR(C5/B5, 0) -> 0.35123542 | E5: =COUNTIF(SalesData[CustomerSegment], A5) -> 125 | F5: =AVERAGEIF(SalesData[CustomerSegment], A5, SalesData[Revenue]) -> 4941.8867
A8: Top 10 Customers by Revenue
A9: Customer Name | B9: Segment | C9: Revenue | D9: Gross Profit | E9: Gross Margin | F9: Flag (<30% Margin & High Rev)
A10: Alpha Corp | B10: Enterprise | C10: =SUMIF(SalesData[CustomerName], A10, SalesData[Revenue]) -> 82948.463 | D10: =SUMIF(SalesData[CustomerName], A10, SalesData[GrossProfit]) -> 29795.123 | E10: =IFERROR(D10/C10, 0) -> 0.35920042 | F10: =IF(AND(C10>AVERAGE($C$10:$C$19), E10<0.3), "Review / Flag", "Normal") -> Normal
A11: Beta LLC | B11: SMB | C11: =SUMIF(SalesData[CustomerName], A11, SalesData[Revenue]) -> 144913.3 | D11: =SUMIF(SalesData[CustomerName], A11, SalesData[GrossProfit]) -> 50719.654 | E11: =IFERROR(D11/C11, 0) -> 0.35 | F11: =IF(AND(C11>AVERAGE($C$10:$C$19), E11<0.3), "Review / Flag", "Normal") -> Normal
A12: Gamma Inc | B12: Consumer | C12: =SUMIF(SalesData[CustomerName], A12, SalesData[Revenue]) -> 144716.23 | D12: =SUMIF(SalesData[CustomerName], A12, SalesData[GrossProfit]) -> 50650.679 | E12: =IFERROR(D12/C12, 0) -> 0.35 | F12: =IF(AND(C12>AVERAGE($C$10:$C$19), E12<0.3), "Review / Flag", "Normal") -> Normal
A13: Delta Retail | B13: Consumer | C13: =SUMIF(SalesData[CustomerName], A13, SalesData[Revenue]) -> 84949.486 | D13: =SUMIF(SalesData[CustomerName], A13, SalesData[GrossProfit]) -> 29732.32 | E13: =IFERROR(D13/C13, 0) -> 0.35 | F13: =IF(AND(C13>AVERAGE($C$10:$C$19), E13<0.3), "Review / Flag", "Normal") -> Normal
A14: Epsilon Group | B14: Enterprise | C14: =SUMIF(SalesData[CustomerName], A14, SalesData[Revenue]) -> 65140.213 | D14: =SUMIF(SalesData[CustomerName], A14, SalesData[GrossProfit]) -> 22799.074 | E14: =IFERROR(D14/C14, 0) -> 0.35 | F14: =IF(AND(C14>AVERAGE($C$10:$C$19), E14<0.3), "Review / Flag", "Normal") -> Normal
A15: Zeta Solutions | B15: SMB | C15: =SUMIF(SalesData[CustomerName], A15, SalesData[Revenue]) -> 137127.85 | D15: =SUMIF(SalesData[CustomerName], A15, SalesData[GrossProfit]) -> 47994.747 | E15: =IFERROR(D15/C15, 0) -> 0.35 | F15: =IF(AND(C15>AVERAGE($C$10:$C$19), E15<0.3), "Review / Flag", "Normal") -> Normal
A16: Omega Tech | B16: Enterprise | C16: =SUMIF(SalesData[CustomerName], A16, SalesData[Revenue]) -> 175712.84 | D16: =SUMIF(SalesData[CustomerName], A16, SalesData[GrossProfit]) -> 61499.495 | E16: =IFERROR(D16/C16, 0) -> 0.35 | F16: =IF(AND(C16>AVERAGE($C$10:$C$19), E16<0.3), "Review / Flag", "Normal") -> Normal
A17: Apex Industries | B17: SMB | C17: =SUMIF(SalesData[CustomerName], A17, SalesData[Revenue]) -> 54134.83 | D17: =SUMIF(SalesData[CustomerName], A17, SalesData[GrossProfit]) -> 18947.19 | E17: =IFERROR(D17/C17, 0) -> 0.35 | F17: =IF(AND(C17>AVERAGE($C$10:$C$19), E17<0.3), "Review / Flag", "Normal") -> Normal
A18: Vertex Partners | B18: Consumer | C18: =SUMIF(SalesData[CustomerName], A18, SalesData[Revenue]) -> 157932.19 | D18: =SUMIF(SalesData[CustomerName], A18, SalesData[GrossProfit]) -> 55276.267 | E18: =IFERROR(D18/C18, 0) -> 0.35 | F18: =IF(AND(C18>AVERAGE($C$10:$C$19), E18<0.3), "Review / Flag", "Normal") -> Normal
A19: Pioneer Media | B19: SMB | C19: =SUMIF(SalesData[CustomerName], A19, SalesData[Revenue]) -> 72743.826 | D19: =SUMIF(SalesData[CustomerName], A19, SalesData[GrossProfit]) -> 25460.339 | E19: =IFERROR(D19/C19, 0) -> 0.35 | F19: =IF(AND(C19>AVERAGE($C$10:$C$19), E19<0.3), "Review / Flag", "Normal") -> Normal

Sheet Inventory & Reorder Analysis
A1: ProductID | B1: ProductName | C1: Category | D1: Supplier | E1: StandardCost | F1: StandardPrice | G1: ReorderLevel | H1: CurrentStock | I1: LeadTimeDays | J1: Stock Status | K1: Estimated Reorder Quantity
A2: ='Product Master'!A2 -> P001 | B2: ='Product Master'!B2 -> Laptop Pro 15 | C2: ='Product Master'!C2 -> Laptops | D2: ='Product Master'!D2 -> TechGlobal | E2: ='Product Master'!E2 -> 1200 | F2: ='Product Master'!F2 -> 1800 | G2: ='Product Master'!G2 -> 20 | H2: ='Product Master'!H2 -> 15 | I2: ='Product Master'!I2 -> 5 | J2: =IF(H2<0.5*G2, "Critical", IF(H2<G2, "Reorder Soon", "Healthy")) -> Reorder Soon | K2: =IF(H2<G2, (G2*2)-H2, 0) -> 25
A3: ='Product Master'!A3 -> P002 | B3: ='Product Master'!B3 -> Smartphone X | C3: ='Product Master'!C3 -> Phones | D3: ='Product Master'!D3 -> MobileSource | E3: ='Product Master'!E3 -> 600 | F3: ='Product Master'!F3 -> 900 | G3: ='Product Master'!G3 -> 50 | H3: ='Product Master'!H3 -> 40 | I3: ='Product Master'!I3 -> 3 | J3: =IF(H3<0.5*G3, "Critical", IF(H3<G3, "Reorder Soon", "Healthy")) -> Reorder Soon | K3: =IF(H3<G3, (G3*2)-H3, 0) -> 60
A4: ='Product Master'!A4 -> P003 | B4: ='Product Master'!B4 -> Wireless Earbuds | C4: ='Product Master'!C4 -> Audio | D4: ='Product Master'!D4 -> SoundWave | E4: ='Product Master'!E4 -> 80 | F4: ='Product Master'!F4 -> 120 | G4: ='Product Master'!G4 -> 100 | H4: ='Product Master'!H4 -> 120 | I4: ='Product Master'!I4 -> 2 | J4: =IF(H4<0.5*G4, "Critical", IF(H4<G4, "Reorder Soon", "Healthy")) -> Healthy | K4: =IF(H4<G4, (G4*2)-H4, 0) -> 0
A5: ='Product Master'!A5 -> P004 | B5: ='Product Master'!B5 -> Mechanical Keyboard | C5: ='Product Master'!C5 -> Accessories | D5: ='Product Master'!D5 -> KeyMasters | E5: ='Product Master'!E5 -> 100 | F5: ='Product Master'!F5 -> 150 | G5: ='Product Master'!G5 -> 30 | H5: ='Product Master'!H5 -> 25 | I5: ='Product Master'!I5 -> 4 | J5: =IF(H5<0.5*G5, "Critical", IF(H5<G5, "Reorder Soon", "Healthy")) -> Reorder Soon | K5: =IF(H5<G5, (G5*2)-H5, 0) -> 35
A6: ='Product Master'!A6 -> P005 | B6: ='Product Master'!B6 -> All-in-One PC | C6: ='Product Master'!C6 -> Office Equipment | D6: ='Product Master'!D6 -> OfficeTech | E6: ='Product Master'!E6 -> 900 | F6: ='Product Master'!F6 -> 1350 | G6: ='Product Master'!G6 -> 15 | H6: ='Product Master'!H6 -> 10 | I6: ='Product Master'!I6 -> 7 | J6: =IF(H6<0.5*G6, "Critical", IF(H6<G6, "Reorder Soon", "Healthy")) -> Reorder Soon | K6: =IF(H6<G6, (G6*2)-H6, 0) -> 20
A7: ='Product Master'!A7 -> P006 | B7: ='Product Master'!B7 -> Gaming Console Gen 5 | C7: ='Product Master'!C7 -> Gaming | D7: ='Product Master'!D7 -> GameWorld | E7: ='Product Master'!E7 -> 400 | F7: ='Product Master'!F7 -> 600 | G7: ='Product Master'!G7 -> 25 | H7: ='Product Master'!H7 -> 30 | I7: ='Product Master'!I7 -> 6 | J7: =IF(H7<0.5*G7, "Critical", IF(H7<G7, "Reorder Soon", "Healthy")) -> Healthy | K7: =IF(H7<G7, (G7*2)-H7, 0) -> 0
A8: ='Product Master'!A8 -> P007 | B8: ='Product Master'!B8 -> Laptop Air 13 | C8: ='Product Master'!C8 -> Laptops | D8: ='Product Master'!D8 -> TechGlobal | E8: ='Product Master'!E8 -> 1000 | F8: ='Product Master'!F8 -> 1500 | G8: ='Product Master'!G8 -> 25 | H8: ='Product Master'!H8 -> 20 | I8: ='Product Master'!I8 -> 5 | J8: =IF(H8<0.5*G8, "Critical", IF(H8<G8, "Reorder Soon", "Healthy")) -> Reorder Soon | K8: =IF(H8<G8, (G8*2)-H8, 0) -> 30
A9: ='Product Master'!A9 -> P008 | B9: ='Product Master'!B9 -> Smartphone Lite | C9: ='Product Master'!C9 -> Phones | D9: ='Product Master'!D9 -> MobileSource | E9: ='Product Master'!E9 -> 300 | F9: ='Product Master'!F9 -> 450 | G9: ='Product Master'!G9 -> 60 | H9: ='Product Master'!H9 -> 70 | I9: ='Product Master'!I9 -> 3 | J9: =IF(H9<0.5*G9, "Critical", IF(H9<G9, "Reorder Soon", "Healthy")) -> Healthy | K9: =IF(H9<G9, (G9*2)-H9, 0) -> 0
A10: ='Product Master'!A10 -> P009 | B10: ='Product Master'!B10 -> Bluetooth Speaker | C10: ='Product Master'!C10 -> Audio | D10: ='Product Master'!D10 -> SoundWave | E10: ='Product Master'!E10 -> 50 | F10: ='Product Master'!F10 -> 75 | G10: ='Product Master'!G10 -> 150 | H10: ='Product Master'!H10 -> 180 | I10: ='Product Master'!I10 -> 2 | J10: =IF(H10<0.5*G10, "Critical", IF(H10<G10, "Reorder Soon", "Healthy")) -> Healthy | K10: =IF(H10<G10, (G10*2)-H10, 0) -> 0
A11: ='Product Master'!A11 -> P010 | B11: ='Product Master'!B11 -> Ergonomic Mouse | C11: ='Product Master'!C11 -> Accessories | D11: ='Product Master'!D11 -> KeyMasters | E11: ='Product Master'!E11 -> 40 | F11: ='Product Master'!F11 -> 60 | G11: ='Product Master'!G11 -> 50 | H11: ='Product Master'!H11 -> 60 | I11: ='Product Master'!I11 -> 2 | J11: =IF(H11<0.5*G11, "Critical", IF(H11<G11, "Reorder Soon", "Healthy")) -> Healthy | K11: =IF(H11<G11, (G11*2)-H11, 0) -> 0
A12: ='Product Master'!A12 -> P011 | B12: ='Product Master'!B12 -> Office Monitor 27" | C12: ='Product Master'!C12 -> Office Equipment | D12: ='Product Master'!D12 -> OfficeTech | E12: ='Product Master'!E12 -> 250 | F12: ='Product Master'!F12 -> 375 | G12: ='Product Master'!G12 -> 20 | H12: ='Product Master'!H12 -> 22 | I12: ='Product Master'!I12 -> 4 | J12: =IF(H12<0.5*G12, "Critical", IF(H12<G12, "Reorder Soon", "Healthy")) -> Healthy | K12: =IF(H12<G12, (G12*2)-H12, 0) -> 0
A13: ='Product Master'!A13 -> P012 | B13: ='Product Master'!B13 -> Gaming Keyboard RGB | C13: ='Product Master'!C13 -> Gaming | D13: ='Product Master'!D13 -> GameWorld | E13: ='Product Master'!E13 -> 120 | F13: ='Product Master'!F13 -> 180 | G13: ='Product Master'!G13 -> 35 | H13: ='Product Master'!H13 -> 40 | I13: ='Product Master'!I13 -> 3 | J13: =IF(H13<0.5*G13, "Critical", IF(H13<G13, "Reorder Soon", "Healthy")) -> Healthy | K13: =IF(H13<G13, (G13*2)-H13, 0) -> 0
... A41: ='Product Master'!A41 -> P040 | B41: ='Product Master'!B41 -> Smartwatch | C41: ='Product Master'!C41 -> Accessories | D41: ='Product Master'!D41 -> WearableTech | E41: ='Product Master'!E41 -> 200 | F41: ='Product Master'!F41 -> 300 | G41: ='Product Master'!G41 -> 60 | H41: ='Product Master'!H41 -> 70 | I41: ='Product Master'!I41 -> 2 | J41: =IF(H41<0.5*G41, "Critical", IF(H41<G41, "Reorder Soon", "Healthy")) -> Healthy | K41: =IF(H41<G41, (G41*2)-H41, 0) -> 0

Sheet Executive Dashboard
A1: Executive Management Dashboard
A3: Total Revenue | C3: Total Gross Profit | E3: Gross Margin % | G3: Units Sold | I3: Average Order Value | K3: Completed Orders
A4: ='Sales Summary'!A4 -> 1788685.3 | C4: ='Sales Summary'!B4 -> 626803.02 | E4: ='Sales Summary'!C4 -> 0.35042666 | G4: ='Sales Summary'!D4 -> 2840
A7: Region Performance Summary | D7: Category Gross Profit Summary | G7: Revenue by Customer Segment
A8: Region | B8: Revenue | D8: Category | E8: Gross Profit | G8: Segment | H8: Revenue
A9: North | D9: Laptops | G9: Consumer
A10: South | D10: Phones | G10: SMB
A11: East | D11: Audio | G11: Enterprise
A12: West | D12: Accessories
D13: Office Equipment
D14: Gaming
A22: Management Insights & Action Items
A23: 1. Laptops and Phones drive over 60% of total gross profit, with Laptops achieving the highest average order value.
A24: 2. West region leads in total revenue generation, outperforming North by approximately 40%.
A25: 3. Customer segment analysis indicates Enterprise accounts yield the highest gross margin stability.
A26: 4. Inventory review highlights SKUs below reorder threshold; immediate replenishment orders have been flagged.
A27: 5. Monthly revenue trends show steady growth, aligning closely with expansion targets in SMB and Enterprise.
