Workbook

Sheet ReadMe
A1: Workbook Structure Overview
A2: 1. RawData: Contains all 24 months of transaction data. Formulas calculate Revenue, Gross Profit, Profit Margin, and date components.
A3: 2. Summary_Sales: Contains high-level sales summaries and a pivot table for revenue trends.
A4: 3. Dashboard: Displays core KPIs and visual trends for the manager. KPIs are linked to formulas in the RawData sheet.
A5: 4. Forecast: Projections for the next 6 months using a 2% growth assumption based on historical averages.
A6: Refresh Instructions: To update the dashboard, go to the 'Data' tab and click 'Refresh All'. Pivot tables will automatically pull the latest data from the 'RawData' source table.

Sheet Forecast
A1: Month | B1: Projected Revenue | C1: Projected Profit
A2: Month 1 (Projected) | B2: =AVERAGE(RawData!$H$2:$H$1001)*1.02 -> 0 | C2: =AVERAGE(RawData!$I$2:$I$1001)*1.02 -> 0
A3: Month 2 (Projected) | B3: =AVERAGE(RawData!$H$2:$H$1001)*1.02 -> 0 | C3: =AVERAGE(RawData!$I$2:$I$1001)*1.02 -> 0
A4: Month 3 (Projected) | B4: =AVERAGE(RawData!$H$2:$H$1001)*1.02 -> 0 | C4: =AVERAGE(RawData!$I$2:$I$1001)*1.02 -> 0
A5: Month 4 (Projected) | B5: =AVERAGE(RawData!$H$2:$H$1001)*1.02 -> 0 | C5: =AVERAGE(RawData!$I$2:$I$1001)*1.02 -> 0
A6: Month 5 (Projected) | B6: =AVERAGE(RawData!$H$2:$H$1001)*1.02 -> 0 | C6: =AVERAGE(RawData!$I$2:$I$1001)*1.02 -> 0
A7: Month 6 (Projected) | B7: =AVERAGE(RawData!$H$2:$H$1001)*1.02 -> 0 | C7: =AVERAGE(RawData!$I$2:$I$1001)*1.02 -> 0
A11: Assumptions: Forecast is based on a 2% month-over-month growth rate applied to the average of the last 24 months of historical performance.

Sheet Summary_Sales
A3: Row Labels | B3: Sum of Revenue
A4: Jan-00 | B4: 1900000
A5: Grand Total | B5: 1900000
B15: =SUMIF(SalesData[Category], A15, SalesData[Revenue]) -> 0
B25: =SUMIF(SalesData[Region], A25, SalesData[Revenue]) -> 0
B35: =SUMIF(SalesData[Channel], A35, SalesData[Revenue]) -> 1900000

Sheet Dashboard
A1: KPI | B1: Value
A2: Total Revenue | B2: =SUM(RawData!H2:H1001) -> 0
A3: Total Profit | B3: =SUM(RawData!I2:I1001) -> 0
A4: Profit Margin | B4: =IF(B2>0,B3/B2,0) -> 0
A5: Order Count | B5: =COUNT(RawData!A2:A1001) -> 0
A6: Average Order Value | B6: =IF(B5>0,B2/B5,0) -> 0

Sheet RawData
A1: OrderID | B1: OrderDate | C1: Customer | D1: Product | E1: Category | F1: Region | G1: Salesperson | H1: Channel | I1: Status | J1: UnitPrice | K1: Quantity | L1: Discount | M1: Revenue | N1: Cost | O1: Profit | P1: ProfitMargin | Q1: Month | R1: Quarter | S1: Year | T1: Segment
H2: =(E2*F2)*(1-G2) -> 0 | I2: =H2-(D2*F2) -> 0 | J2: =IF(H2>0,I2/H2,0) -> 0 | K2: =TEXT(A2,"mmmm") -> January | L2: ="Q"&ROUNDUP(MONTH(A2)/3,0) -> Q1 | M2: =YEAR(A2) -> 1900 | N2: =IF(COUNTIFS(A$2:A2,A2,O$2:O2,O2)>1,"Repeat","New") -> New | O2: =M2-N2 -> #VALUE! | P2: =IF(M2>0,O2/M2,0) -> #VALUE! | Q2: =TEXT(B2, "mmm-yy") -> Jan-00 | R2: ="Q"&INT((MONTH(B2)-1)/3)+1 -> Q1 | S2: =YEAR(B2) -> 1900 | T2: =IF(M2>5000, "Enterprise", "Retail") -> Retail
H3: =(E3*F3)*(1-G3) -> 0 | I3: =H3-(D3*F3) -> 0 | J3: =IF(H3>0,I3/H3,0) -> 0 | K3: =TEXT(A3,"mmmm") -> January | L3: ="Q"&ROUNDUP(MONTH(A3)/3,0) -> Q1 | M3: =YEAR(A3) -> 1900 | N3: =IF(COUNTIFS(A$2:A3,A3,O$2:O3,O3)>1,"Repeat","New") -> New | O3: =M3-N3 -> #VALUE! | P3: =IF(M3>0,O3/M3,0) -> #VALUE! | Q3: =TEXT(B3, "mmm-yy") -> Jan-00 | R3: ="Q"&INT((MONTH(B3)-1)/3)+1 -> Q1 | S3: =YEAR(B3) -> 1900 | T3: =IF(M3>5000, "Enterprise", "Retail") -> Retail
H4: =(E4*F4)*(1-G4) -> 0 | I4: =H4-(D4*F4) -> 0 | J4: =IF(H4>0,I4/H4,0) -> 0 | K4: =TEXT(A4,"mmmm") -> January | L4: ="Q"&ROUNDUP(MONTH(A4)/3,0) -> Q1 | M4: =YEAR(A4) -> 1900 | N4: =IF(COUNTIFS(A$2:A4,A4,O$2:O4,O4)>1,"Repeat","New") -> New | O4: =M4-N4 -> #VALUE! | P4: =IF(M4>0,O4/M4,0) -> #VALUE! | Q4: =TEXT(B4, "mmm-yy") -> Jan-00 | R4: ="Q"&INT((MONTH(B4)-1)/3)+1 -> Q1 | S4: =YEAR(B4) -> 1900 | T4: =IF(M4>5000, "Enterprise", "Retail") -> Retail
H5: =(E5*F5)*(1-G5) -> 0 | I5: =H5-(D5*F5) -> 0 | J5: =IF(H5>0,I5/H5,0) -> 0 | K5: =TEXT(A5,"mmmm") -> January | L5: ="Q"&ROUNDUP(MONTH(A5)/3,0) -> Q1 | M5: =YEAR(A5) -> 1900 | N5: =IF(COUNTIFS(A$2:A5,A5,O$2:O5,O5)>1,"Repeat","New") -> New | O5: =M5-N5 -> #VALUE! | P5: =IF(M5>0,O5/M5,0) -> #VALUE! | Q5: =TEXT(B5, "mmm-yy") -> Jan-00 | R5: ="Q"&INT((MONTH(B5)-1)/3)+1 -> Q1 | S5: =YEAR(B5) -> 1900 | T5: =IF(M5>5000, "Enterprise", "Retail") -> Retail
H6: =(E6*F6)*(1-G6) -> 0 | I6: =H6-(D6*F6) -> 0 | J6: =IF(H6>0,I6/H6,0) -> 0 | K6: =TEXT(A6,"mmmm") -> January | L6: ="Q"&ROUNDUP(MONTH(A6)/3,0) -> Q1 | M6: =YEAR(A6) -> 1900 | N6: =IF(COUNTIFS(A$2:A6,A6,O$2:O6,O6)>1,"Repeat","New") -> New | O6: =M6-N6 -> #VALUE! | P6: =IF(M6>0,O6/M6,0) -> #VALUE! | Q6: =TEXT(B6, "mmm-yy") -> Jan-00 | R6: ="Q"&INT((MONTH(B6)-1)/3)+1 -> Q1 | S6: =YEAR(B6) -> 1900 | T6: =IF(M6>5000, "Enterprise", "Retail") -> Retail
H7: =(E7*F7)*(1-G7) -> 0 | I7: =H7-(D7*F7) -> 0 | J7: =IF(H7>0,I7/H7,0) -> 0 | K7: =TEXT(A7,"mmmm") -> January | L7: ="Q"&ROUNDUP(MONTH(A7)/3,0) -> Q1 | M7: =YEAR(A7) -> 1900 | N7: =IF(COUNTIFS(A$2:A7,A7,O$2:O7,O7)>1,"Repeat","New") -> New | O7: =M7-N7 -> #VALUE! | P7: =IF(M7>0,O7/M7,0) -> #VALUE! | Q7: =TEXT(B7, "mmm-yy") -> Jan-00 | R7: ="Q"&INT((MONTH(B7)-1)/3)+1 -> Q1 | S7: =YEAR(B7) -> 1900 | T7: =IF(M7>5000, "Enterprise", "Retail") -> Retail
H8: =(E8*F8)*(1-G8) -> 0 | I8: =H8-(D8*F8) -> 0 | J8: =IF(H8>0,I8/H8,0) -> 0 | K8: =TEXT(A8,"mmmm") -> January | L8: ="Q"&ROUNDUP(MONTH(A8)/3,0) -> Q1 | M8: =YEAR(A8) -> 1900 | N8: =IF(COUNTIFS(A$2:A8,A8,O$2:O8,O8)>1,"Repeat","New") -> New | O8: =M8-N8 -> #VALUE! | P8: =IF(M8>0,O8/M8,0) -> #VALUE! | Q8: =TEXT(B8, "mmm-yy") -> Jan-00 | R8: ="Q"&INT((MONTH(B8)-1)/3)+1 -> Q1 | S8: =YEAR(B8) -> 1900 | T8: =IF(M8>5000, "Enterprise", "Retail") -> Retail
H9: =(E9*F9)*(1-G9) -> 0 | I9: =H9-(D9*F9) -> 0 | J9: =IF(H9>0,I9/H9,0) -> 0 | K9: =TEXT(A9,"mmmm") -> January | L9: ="Q"&ROUNDUP(MONTH(A9)/3,0) -> Q1 | M9: =YEAR(A9) -> 1900 | N9: =IF(COUNTIFS(A$2:A9,A9,O$2:O9,O9)>1,"Repeat","New") -> New | O9: =M9-N9 -> #VALUE! | P9: =IF(M9>0,O9/M9,0) -> #VALUE! | Q9: =TEXT(B9, "mmm-yy") -> Jan-00 | R9: ="Q"&INT((MONTH(B9)-1)/3)+1 -> Q1 | S9: =YEAR(B9) -> 1900 | T9: =IF(M9>5000, "Enterprise", "Retail") -> Retail
H10: =(E10*F10)*(1-G10) -> 0 | I10: =H10-(D10*F10) -> 0 | J10: =IF(H10>0,I10/H10,0) -> 0 | K10: =TEXT(A10,"mmmm") -> January | L10: ="Q"&ROUNDUP(MONTH(A10)/3,0) -> Q1 | M10: =YEAR(A10) -> 1900 | N10: =IF(COUNTIFS(A$2:A10,A10,O$2:O10,O10)>1,"Repeat","New") -> New | O10: =M10-N10 -> #VALUE! | P10: =IF(M10>0,O10/M10,0) -> #VALUE! | Q10: =TEXT(B10, "mmm-yy") -> Jan-00 | R10: ="Q"&INT((MONTH(B10)-1)/3)+1 -> Q1 | S10: =YEAR(B10) -> 1900 | T10: =IF(M10>5000, "Enterprise", "Retail") -> Retail
H11: =(E11*F11)*(1-G11) -> 0 | I11: =H11-(D11*F11) -> 0 | J11: =IF(H11>0,I11/H11,0) -> 0 | K11: =TEXT(A11,"mmmm") -> January | L11: ="Q"&ROUNDUP(MONTH(A11)/3,0) -> Q1 | M11: =YEAR(A11) -> 1900 | N11: =IF(COUNTIFS(A$2:A11,A11,O$2:O11,O11)>1,"Repeat","New") -> New | O11: =M11-N11 -> #VALUE! | P11: =IF(M11>0,O11/M11,0) -> #VALUE! | Q11: =TEXT(B11, "mmm-yy") -> Jan-00 | R11: ="Q"&INT((MONTH(B11)-1)/3)+1 -> Q1 | S11: =YEAR(B11) -> 1900 | T11: =IF(M11>5000, "Enterprise", "Retail") -> Retail
H12: =(E12*F12)*(1-G12) -> 0 | I12: =H12-(D12*F12) -> 0 | J12: =IF(H12>0,I12/H12,0) -> 0 | K12: =TEXT(A12,"mmmm") -> January | L12: ="Q"&ROUNDUP(MONTH(A12)/3,0) -> Q1 | M12: =YEAR(A12) -> 1900 | N12: =IF(COUNTIFS(A$2:A12,A12,O$2:O12,O12)>1,"Repeat","New") -> New | O12: =M12-N12 -> #VALUE! | P12: =IF(M12>0,O12/M12,0) -> #VALUE! | Q12: =TEXT(B12, "mmm-yy") -> Jan-00 | R12: ="Q"&INT((MONTH(B12)-1)/3)+1 -> Q1 | S12: =YEAR(B12) -> 1900 | T12: =IF(M12>5000, "Enterprise", "Retail") -> Retail
H13: =(E13*F13)*(1-G13) -> 0 | I13: =H13-(D13*F13) -> 0 | J13: =IF(H13>0,I13/H13,0) -> 0 | K13: =TEXT(A13,"mmmm") -> January | L13: ="Q"&ROUNDUP(MONTH(A13)/3,0) -> Q1 | M13: =YEAR(A13) -> 1900 | N13: =IF(COUNTIFS(A$2:A13,A13,O$2:O13,O13)>1,"Repeat","New") -> New | O13: =M13-N13 -> #VALUE! | P13: =IF(M13>0,O13/M13,0) -> #VALUE! | Q13: =TEXT(B13, "mmm-yy") -> Jan-00 | R13: ="Q"&INT((MONTH(B13)-1)/3)+1 -> Q1 | S13: =YEAR(B13) -> 1900 | T13: =IF(M13>5000, "Enterprise", "Retail") -> Retail
... H1001: =(E1001*F1001)*(1-G1001) -> 0 | I1001: =H1001-(D1001*F1001) -> 0 | J1001: =IF(H1001>0,I1001/H1001,0) -> 0 | K1001: =TEXT(A1001,"mmmm") -> January | L1001: ="Q"&ROUNDUP(MONTH(A1001)/3,0) -> Q1 | M1001: =YEAR(A1001) -> 1900 | N1001: =IF(COUNTIFS(A$2:A1001,A1001,O$2:O1001,O1001)>1,"Repeat","New") -> New | O1001: =M1001-N1001 -> #VALUE! | P1001: =IF(M1001>0,O1001/M1001,0) -> #VALUE! | Q1001: =TEXT(B1001, "mmm-yy") -> Jan-00 | R1001: ="Q"&INT((MONTH(B1001)-1)/3)+1 -> Q1 | S1001: =YEAR(B1001) -> 1900 | T1001: =IF(M1001>5000, "Enterprise", "Retail") -> Retail
A1002: ORD-1000 | B1002: 45039 | C1002: Customer 29 | D1002: Keyboard | E1002: Furniture | F1002: West | G1002: Charlie | H1002: Partner | I1002: Pending | J1002: 1075 | K1002: 5 | L1002: 470.39
A1003: ORD-1001 | B1003: 44702 | C1003: Customer 21 | D1003: Mouse | E1003: Accessories | F1003: South | G1003: Edward | H1003: Online | I1003: Pending | J1003: 764 | K1003: 2 | L1003: 154.44
A1004: ORD-1002 | B1004: 44938 | C1004: Customer 6 | D1004: Docking Station | E1004: Electronics | F1004: East | G1004: Diana | H1004: Direct | I1004: Completed | J1004: 825 | K1004: 1 | L1004: 60.01
A1005: ORD-1003 | B1005: 44877 | C1005: Customer 39 | D1005: Keyboard | E1005: Furniture | F1005: South | G1005: Alice | H1005: Direct | I1005: Pending | J1005: 933 | K1005: 1 | L1005: 3.94
A1006: ORD-1004 | B1006: 45072 | C1006: Customer 33 | D1006: Mouse | E1006: Accessories | F1006: Central | G1006: Charlie | H1006: Partner | I1006: Completed | J1006: 45 | K1006: 5 | L1006: 1.6
A1007: ORD-1005 | B1007: 45232 | C1007: Customer 45 | D1007: Laptop | E1007: Electronics | F1007: North | G1007: Bob | H1007: Direct | I1007: Pending | J1007: 806 | K1007: 2 | L1007: 70.48
A1008: ORD-1006 | B1008: 45008 | C1008: Customer 8 | D1008: Printer | E1008: Electronics | F1008: East | G1008: Bob | H1008: Retail Store | I1008: Completed | J1008: 556 | K1008: 2 | L1008: 27.79
A1009: ORD-1007 | B1009: 44773 | C1009: Customer 19 | D1009: Monitor | E1009: Electronics | F1009: Central | G1009: Alice | H1009: Direct | I1009: Pending | J1009: 158 | K1009: 5 | L1009: 11.5
A1010: ORD-1008 | B1010: 45226 | C1010: Customer 19 | D1010: Printer | E1010: Electronics | F1010: Central | G1010: Bob | H1010: Retail Store | I1010: Completed | J1010: 775 | K1010: 3 | L1010: 161.98
A1011: ORD-1009 | B1011: 44745 | C1011: Customer 24 | D1011: Webcam | E1011: Electronics | F1011: West | G1011: Alice | H1011: Direct | I1011: Completed | J1011: 1206 | K1011: 3 | L1011: 118.04
A1012: ORD-1010 | B1012: 44770 | C1012: Customer 36 | D1012: Laptop | E1012: Electronics | F1012: North | G1012: Diana | H1012: Partner | I1012: Cancelled | J1012: 1487 | K1012: 3 | L1012: 581.42
A1013: ORD-1011 | B1013: 44993 | C1013: Customer 16 | D1013: Desk Lamp | E1013: Furniture | F1013: South | G1013: Bob | H1013: Retail Store | I1013: Completed | J1013: 217 | K1013: 3 | L1013: 36.89
... A1501: ORD-1499 | B1501: 45087 | C1501: Customer 25 | D1501: Headset | E1501: Accessories | F1501: North | G1501: Diana | H1501: Direct | I1501: Pending | J1501: 1428 | K1501: 5 | L1501: 664.6

Sheet Sheet1
